[
	{
		"name": "Preston",
		"age": 153,
		"country": "Mauritania"
	},
	{
		"name": "Otto",
		"age": 108,
		"country": "Brunei"
	},
	{
		"name": "Zenaida",
		"age": 18,
		"country": "Korea, North"
	},
	{
		"name": "Colton",
		"age": 17,
		"country": "Falkland Islands"
	},
	{
		"name": "Tamekah",
		"age": 103,
		"country": "Honduras"
	},
	{
		"name": "Colorado",
		"age": 172,
		"country": "Gibraltar"
	},
	{
		"name": "Naida",
		"age": 53,
		"country": "United States"
	},
	{
		"name": "Xerxes",
		"age": 140,
		"country": "Paraguay"
	},
	{
		"name": "MacKensie",
		"age": 74,
		"country": "Syria"
	},
	{
		"name": "Mariko",
		"age": 104,
		"country": "Maldives"
	},
	{
		"name": "Colleen",
		"age": 109,
		"country": "Martinique"
	},
	{
		"name": "Acton",
		"age": 105,
		"country": "Denmark"
	},
	{
		"name": "Hashim",
		"age": 33,
		"country": "Comoros"
	},
	{
		"name": "Tatum",
		"age": 122,
		"country": "Bonaire, Sint Eustatius and Saba"
	},
	{
		"name": "Tiger",
		"age": 152,
		"country": "New Zealand"
	},
	{
		"name": "Rashad",
		"age": 192,
		"country": "Sao Tome and Principe"
	},
	{
		"name": "Angela",
		"age": 13,
		"country": "Guyana"
	},
	{
		"name": "Shaine",
		"age": 147,
		"country": "Saint Helena, Ascension and Tristan da Cunha"
	},
	{
		"name": "Kevyn",
		"age": 173,
		"country": "South Georgia and The South Sandwich Islands"
	},
	{
		"name": "Hyatt",
		"age": 9,
		"country": "Cyprus"
	},
	{
		"name": "Bevis",
		"age": 93,
		"country": "Viet Nam"
	},
	{
		"name": "Alea",
		"age": 39,
		"country": "Christmas Island"
	},
	{
		"name": "Bruno",
		"age": 67,
		"country": "Bangladesh"
	},
	{
		"name": "April",
		"age": 78,
		"country": "Åland Islands"
	},
	{
		"name": "Cole",
		"age": 17,
		"country": "Croatia"
	},
	{
		"name": "Reece",
		"age": 66,
		"country": "Virgin Islands, United States"
	},
	{
		"name": "Duncan",
		"age": 72,
		"country": "Turks and Caicos Islands"
	},
	{
		"name": "Omar",
		"age": 19,
		"country": "Uruguay"
	},
	{
		"name": "Britanney",
		"age": 127,
		"country": "Lebanon"
	},
	{
		"name": "Fulton",
		"age": 25,
		"country": "Cyprus"
	},
	{
		"name": "Clementine",
		"age": 117,
		"country": "Yemen"
	},
	{
		"name": "Harding",
		"age": 179,
		"country": "Australia"
	},
	{
		"name": "Fulton",
		"age": 104,
		"country": "Bahamas"
	},
	{
		"name": "Dale",
		"age": 192,
		"country": "Kyrgyzstan"
	},
	{
		"name": "Ocean",
		"age": 88,
		"country": "Bahrain"
	},
	{
		"name": "Sydney",
		"age": 44,
		"country": "Georgia"
	},
	{
		"name": "Lester",
		"age": 97,
		"country": "Kenya"
	},
	{
		"name": "Kenyon",
		"age": 124,
		"country": "Russian Federation"
	},
	{
		"name": "Barrett",
		"age": 145,
		"country": "Maldives"
	},
	{
		"name": "Phelan",
		"age": 108,
		"country": "Azerbaijan"
	},
	{
		"name": "Harper",
		"age": 199,
		"country": "Paraguay"
	},
	{
		"name": "Omar",
		"age": 32,
		"country": "Kuwait"
	},
	{
		"name": "Natalie",
		"age": 200,
		"country": "Fiji"
	},
	{
		"name": "Carolyn",
		"age": 30,
		"country": "Malawi"
	},
	{
		"name": "Ian",
		"age": 42,
		"country": "Svalbard and Jan Mayen Islands"
	},
	{
		"name": "Aline",
		"age": 67,
		"country": "Saint Kitts and Nevis"
	},
	{
		"name": "Maggie",
		"age": 24,
		"country": "San Marino"
	},
	{
		"name": "Griffith",
		"age": 93,
		"country": "India"
	},
	{
		"name": "Kathleen",
		"age": 5,
		"country": "Mongolia"
	},
	{
		"name": "Hermione",
		"age": 74,
		"country": "Timor-Leste"
	},
	{
		"name": "May",
		"age": 161,
		"country": "Grenada"
	},
	{
		"name": "Cameron",
		"age": 3,
		"country": "Guernsey"
	},
	{
		"name": "Cora",
		"age": 152,
		"country": "Saudi Arabia"
	},
	{
		"name": "Thane",
		"age": 23,
		"country": "Costa Rica"
	},
	{
		"name": "Ina",
		"age": 192,
		"country": "Cayman Islands"
	},
	{
		"name": "Quamar",
		"age": 20,
		"country": "Ethiopia"
	},
	{
		"name": "Caesar",
		"age": 183,
		"country": "Eritrea"
	},
	{
		"name": "Nicholas",
		"age": 76,
		"country": "Tajikistan"
	},
	{
		"name": "Olympia",
		"age": 188,
		"country": "Dominican Republic"
	},
	{
		"name": "Lucas",
		"age": 121,
		"country": "Cook Islands"
	},
	{
		"name": "Maryam",
		"age": 143,
		"country": "Netherlands"
	},
	{
		"name": "Yvette",
		"age": 3,
		"country": "Mauritius"
	},
	{
		"name": "Alfreda",
		"age": 12,
		"country": "United Kingdom (Great Britain)"
	},
	{
		"name": "Bryar",
		"age": 26,
		"country": "Burundi"
	},
	{
		"name": "Nathaniel",
		"age": 65,
		"country": "Saudi Arabia"
	},
	{
		"name": "Fuller",
		"age": 165,
		"country": "United Kingdom (Great Britain)"
	},
	{
		"name": "Amena",
		"age": 186,
		"country": "Mexico"
	},
	{
		"name": "Sade",
		"age": 177,
		"country": "Guinea-Bissau"
	},
	{
		"name": "Ulric",
		"age": 142,
		"country": "Panama"
	},
	{
		"name": "Keelie",
		"age": 21,
		"country": "Saint Kitts and Nevis"
	},
	{
		"name": "Ebony",
		"age": 38,
		"country": "Jersey"
	},
	{
		"name": "Casey",
		"age": 186,
		"country": "Tajikistan"
	},
	{
		"name": "Theodore",
		"age": 74,
		"country": "Azerbaijan"
	},
	{
		"name": "Ruth",
		"age": 131,
		"country": "Tokelau"
	},
	{
		"name": "Matthew",
		"age": 90,
		"country": "Turks and Caicos Islands"
	},
	{
		"name": "Chaim",
		"age": 35,
		"country": "Togo"
	},
	{
		"name": "Zachary",
		"age": 158,
		"country": "Eritrea"
	},
	{
		"name": "Beau",
		"age": 41,
		"country": "Svalbard and Jan Mayen Islands"
	},
	{
		"name": "Brett",
		"age": 105,
		"country": "Bouvet Island"
	},
	{
		"name": "Eliana",
		"age": 191,
		"country": "Peru"
	},
	{
		"name": "Orson",
		"age": 165,
		"country": "Norfolk Island"
	},
	{
		"name": "Nichole",
		"age": 80,
		"country": "Cook Islands"
	},
	{
		"name": "Barclay",
		"age": 158,
		"country": "Kiribati"
	},
	{
		"name": "Simone",
		"age": 97,
		"country": "China"
	},
	{
		"name": "Zorita",
		"age": 35,
		"country": "Bahrain"
	},
	{
		"name": "Azalia",
		"age": 182,
		"country": "Angola"
	},
	{
		"name": "Nayda",
		"age": 177,
		"country": "Saint Lucia"
	},
	{
		"name": "Cain",
		"age": 130,
		"country": "Dominican Republic"
	},
	{
		"name": "Shoshana",
		"age": 190,
		"country": "Macedonia"
	},
	{
		"name": "Vaughan",
		"age": 10,
		"country": "Sint Maarten"
	},
	{
		"name": "Maxine",
		"age": 57,
		"country": "Faroe Islands"
	},
	{
		"name": "Nash",
		"age": 53,
		"country": "New Zealand"
	},
	{
		"name": "Kermit",
		"age": 10,
		"country": "French Guiana"
	},
	{
		"name": "Quyn",
		"age": 85,
		"country": "Hong Kong"
	},
	{
		"name": "Moses",
		"age": 25,
		"country": "Serbia"
	},
	{
		"name": "Vernon",
		"age": 180,
		"country": "Seychelles"
	},
	{
		"name": "Dante",
		"age": 40,
		"country": "Tajikistan"
	},
	{
		"name": "Flynn",
		"age": 139,
		"country": "Malawi"
	},
	{
		"name": "Hanna",
		"age": 124,
		"country": "Åland Islands"
	},
	{
		"name": "Raymond",
		"age": 189,
		"country": "Palestine, State of"
	}
]